CONTRIBUTING.md
MANIFEST.in
README.rst
setup.py
docs/HISTORY.txt
docs/LICENSE.GPL
docs/LICENSE.txt
docs/dev/README.rst
eea/__init__.py
eea.googlecharts.egg-info/PKG-INFO
eea.googlecharts.egg-info/SOURCES.txt
eea.googlecharts.egg-info/dependency_links.txt
eea.googlecharts.egg-info/entry_points.txt
eea.googlecharts.egg-info/namespace_packages.txt
eea.googlecharts.egg-info/not-zip-safe
eea.googlecharts.egg-info/requires.txt
eea.googlecharts.egg-info/top_level.txt
eea/googlecharts/README.txt
eea/googlecharts/__init__.py
eea/googlecharts/common.zcml
eea/googlecharts/config.py
eea/googlecharts/configure.zcml
eea/googlecharts/interfaces.py
eea/googlecharts/meta.zcml
eea/googlecharts/plone.zcml
eea/googlecharts/profiles.zcml
eea/googlecharts/version.txt
eea/googlecharts/zope2.zcml
eea/googlecharts/browser/__init__.py
eea/googlecharts/browser/configure.zcml
eea/googlecharts/browser/migrate.py
eea/googlecharts/browser/res/__init__.py
eea/googlecharts/browser/res/configure.zcml
eea/googlecharts/browser/res/resources.py
eea/googlecharts/cache/__init__.py
eea/googlecharts/cache/cache.py
eea/googlecharts/cache/configure.zcml
eea/googlecharts/cache/nocache.py
eea/googlecharts/controlpanel/__init__.py
eea/googlecharts/controlpanel/configure.zcml
eea/googlecharts/controlpanel/controlpanel.py
eea/googlecharts/events/__init__.py
eea/googlecharts/events/charts.py
eea/googlecharts/events/configure.zcml
eea/googlecharts/events/interfaces.py
eea/googlecharts/events/subscribers.py
eea/googlecharts/locales/eea.pot
eea/googlecharts/locales/update.sh
eea/googlecharts/locales/bg/LC_MESSAGES/eea.po
eea/googlecharts/locales/cs/LC_MESSAGES/eea.po
eea/googlecharts/locales/da/LC_MESSAGES/eea.po
eea/googlecharts/locales/de/LC_MESSAGES/eea.po
eea/googlecharts/locales/el/LC_MESSAGES/eea.po
eea/googlecharts/locales/en/LC_MESSAGES/eea.po
eea/googlecharts/locales/es/LC_MESSAGES/eea.po
eea/googlecharts/locales/et/LC_MESSAGES/eea.po
eea/googlecharts/locales/eu/LC_MESSAGES/eea.po
eea/googlecharts/locales/fi/LC_MESSAGES/eea.po
eea/googlecharts/locales/fr/LC_MESSAGES/eea.po
eea/googlecharts/locales/hu/LC_MESSAGES/eea.po
eea/googlecharts/locales/is/LC_MESSAGES/eea.po
eea/googlecharts/locales/it/LC_MESSAGES/eea.po
eea/googlecharts/locales/kl/LC_MESSAGES/eea.po
eea/googlecharts/locales/lt/LC_MESSAGES/eea.po
