Metadata-Version: 2.1
Name: eea.googlecharts
Version: 20.8
Summary: Configurator for GoogleCharts
Home-page: https://github.com/collective/eea.googlecharts
Author: European Environment Agency: IDM2 A-Team
Author-email: eea-edw-a-team-alerts@googlegroups.com
License: GPL
Download-URL: https://pypi.python.org/pypi/eea.googlecharts
Keywords: EEA google chart Add-ons Plone Zope
Platform: UNKNOWN
Classifier: Framework :: Zope2
Classifier: Framework :: Plone
Classifier: Framework :: Plone :: 4.0
Classifier: Framework :: Plone :: 4.1
Classifier: Framework :: Plone :: 4.2
Classifier: Framework :: Plone :: 4.3
Classifier: Programming Language :: Zope
Classifier: Programming Language :: Python
Classifier: Programming Language :: Python :: 2.7
Classifier: Topic :: Software Development :: Libraries :: Python Modules
Classifier: License :: OSI Approved :: GNU General Public License (GPL)
Provides-Extra: test
Provides-Extra: zope2
